pymoot/__init__.py
pymoot/auth.py
pymoot/connector.py
pymoot/url.py
pymoot/model/__init__.py
pymoot/model/coordinate.py
pymoot/model/difficulty.py
pymoot/model/highlight.py
pymoot/model/komoot_image.py
pymoot/model/segment.py
pymoot/model/segment_information.py
pymoot/model/sport_type.py
pymoot/model/surface.py
pymoot/model/tour.py
pymoot/model/tour_information.py
pymoot/model/tour_summary.py
pymoot/model/way_type.py
pymoot/model/waypoint.py
PyMoot-1.1.3.dist-info/LICENCE
PyMoot-1.1.3.dist-info/METADATA
PyMoot-1.1.3.dist-info/WHEEL
PyMoot-1.1.3.dist-info/top_level.txt
PyMoot-1.1.3.dist-info/RECORD
