Metadata-Version: 2.1
Name: PyMoot
Version: 1.1.3
Summary: Python wrapper for Komoot APIs
Author-email: Floréal Cabanettes <contacter@alypie.fr>
License: GPLv3
Project-URL: homepage, https://gite.alypie.fr/veloroots/pymoot
Project-URL: repository, https://gite.alypie.fr/veloroots/pymoot
Keywords: komoot,api,python
Requires-Python: >=3.11
License-File: LICENCE
Requires-Dist: dateutils>=0.6.12
Requires-Dist: python-dateutil>=2.8.2
Requires-Dist: requests>=2.31.0
Requires-Dist: pillow>=10.1.0
Requires-Dist: gpxpy>=1.6.1
Requires-Dist: fit-tool>=0.9.13
